StorageCLI/CustomComponents/OptionalPrompt.py
StorageCLI/CustomComponents/__init__.py
StorageCLI/__init__.py
StorageCLI/config.py
StorageCLI/exceptions.py
StorageCLI/sdk.py
StorageCLI/storage_io.py
StorageCLI/utils.py
StorageCLI/validator.py
storagecli-0.1.3.dist-info/LICENSE
storagecli-0.1.3.dist-info/METADATA
storagecli-0.1.3.dist-info/WHEEL
storagecli-0.1.3.dist-info/entry_points.txt
storagecli-0.1.3.dist-info/RECORD
