Metadata-Version: 2.1
Name: storagecli
Version: 0.1.3
Summary: CLI for Storage at app.merklebot.com
Home-page: https://github.com/merklebot/StorageCLI
License: MIT
Author: Arseniy Popov
Author-email: arseniy@merklebot.com
Requires-Python: >=3.7,<4.0
Classifier: License :: OSI Approved :: MIT License
Classifier: Programming Language :: Python :: 3
Classifier: Programming Language :: Python :: 3.7
Classifier: Programming Language :: Python :: 3.8
Classifier: Programming Language :: Python :: 3.9
Classifier: Programming Language :: Python :: 3.10
Classifier: Programming Language :: Python :: 3.11
Classifier: Programming Language :: Python :: 3.12
Requires-Dist: click (>=8.1.7,<9.0.0)
Requires-Dist: platformdirs (>=3.11.0,<4.0.0)
Requires-Dist: requests (>=2.31.0,<3.0.0)
Requires-Dist: tqdm (>=4.66.1,<5.0.0)
Project-URL: Repository, https://github.com/merklebot/StorageCLI
